Metadata-Version: 2.1
Name: orbis-plugin-scoring-wl-harvest-scorer
Version: 2.2.4
Summary: The Weblyzard Harvest Scroring plugin for Orbis
Home-page: https://github.com/orbis-eval/orbis_plugin_scoring_wl_harvest_scorer
Author: fabod
License: GPL2
Platform: UNKNOWN
Requires-Python: >3.6
Requires-Dist: python-Levenshtein
Requires-Dist: editdistance
Requires-Dist: fuzzywuzzy
Requires-Dist: nilsimsa
Requires-Dist: sklearn
